mlpype/hyperopt/__init__.py
mlpype/hyperopt/optimise.py
mlpype_hyperopt-0.6.12.dist-info/METADATA
mlpype_hyperopt-0.6.12.dist-info/WHEEL
mlpype_hyperopt-0.6.12.dist-info/RECORD
